__init__.py
models.py
scraper4ai.py
scraper4ai-1.0.0.dist-info/METADATA
scraper4ai-1.0.0.dist-info/WHEEL
scraper4ai-1.0.0.dist-info/top_level.txt
scraper4ai-1.0.0.dist-info/RECORD
