Metadata-Version: 2.4
Name: scraper4ai
Version: 1.0.0
Summary: This is a scraper for LLM.
Author-email: Keisuke Miyamoto <aichiboyhighschool@gmain.com>
Requires-Python: >=3.7
Requires-Dist: aiofiles
Requires-Dist: aiohappyeyeballs
Requires-Dist: aiohttp
Requires-Dist: aiosignal
Requires-Dist: aiosqlite
Requires-Dist: alphashape
Requires-Dist: annotated-types
Requires-Dist: anyio
Requires-Dist: attrs
Requires-Dist: beautifulsoup4
Requires-Dist: Brotli
Requires-Dist: certifi
Requires-Dist: cffi
Requires-Dist: chardet
Requires-Dist: charset-normalizer
Requires-Dist: click
Requires-Dist: click-log
Requires-Dist: cloudscraper
Requires-Dist: colorama
Requires-Dist: Crawl4AI
Requires-Dist: cryptography
Requires-Dist: cssselect
Requires-Dist: curl_cffi
Requires-Dist: Deprecated
Requires-Dist: distro
Requires-Dist: fake-http-header
Requires-Dist: fake-useragent
Requires-Dist: filelock
Requires-Dist: frozenlist
Requires-Dist: fsspec
Requires-Dist: greenlet
Requires-Dist: h11
Requires-Dist: h2
Requires-Dist: hf-xet
Requires-Dist: hpack
Requires-Dist: httpcore
Requires-Dist: httpx
Requires-Dist: huggingface-hub
Requires-Dist: humanize
Requires-Dist: hyperframe
Requires-Dist: idna
Requires-Dist: importlib_metadata
Requires-Dist: Jinja2
Requires-Dist: jiter
Requires-Dist: joblib
Requires-Dist: jsonschema
Requires-Dist: jsonschema-specifications
Requires-Dist: lark
Requires-Dist: litellm
Requires-Dist: lxml
Requires-Dist: markdown-it-py
Requires-Dist: markdownify
Requires-Dist: MarkupSafe
Requires-Dist: mdurl
Requires-Dist: mpmath
Requires-Dist: multidict
Requires-Dist: networkx
Requires-Dist: nltk
Requires-Dist: numpy
Requires-Dist: openai
Requires-Dist: outcome
Requires-Dist: packaging
Requires-Dist: pillow
Requires-Dist: playwright
Requires-Dist: propcache
Requires-Dist: psutil
Requires-Dist: pycparser
Requires-Dist: pydantic
Requires-Dist: pydantic_core
Requires-Dist: pyee
Requires-Dist: Pygments
Requires-Dist: pyOpenSSL
Requires-Dist: pyparsing
Requires-Dist: pyperclip
Requires-Dist: PySocks
Requires-Dist: python-dotenv
Requires-Dist: PyYAML
Requires-Dist: rank-bm25
Requires-Dist: referencing
Requires-Dist: regex
Requires-Dist: requests
Requires-Dist: requests-toolbelt
Requires-Dist: rich
Requires-Dist: rpds-py
Requires-Dist: rtree
Requires-Dist: safetensors
Requires-Dist: scikit-learn
Requires-Dist: scipy
Requires-Dist: selenium
Requires-Dist: sentence-transformers
Requires-Dist: setuptools
Requires-Dist: shapely
Requires-Dist: six
Requires-Dist: sniffio
Requires-Dist: snowballstemmer
Requires-Dist: sortedcontainers
Requires-Dist: soupsieve
Requires-Dist: sympy
Requires-Dist: tf-playwright-stealth
Requires-Dist: threadpoolctl
Requires-Dist: tiktoken
Requires-Dist: tokenizers
Requires-Dist: torch
Requires-Dist: tqdm
Requires-Dist: transformers
Requires-Dist: trimesh
Requires-Dist: trio
Requires-Dist: trio-websocket
Requires-Dist: typing-inspection
Requires-Dist: typing_extensions
Requires-Dist: undetected-chromedriver
Requires-Dist: urllib3
Requires-Dist: websocket-client
Requires-Dist: websockets
Requires-Dist: wrapt
Requires-Dist: wsproto
Requires-Dist: xxhash
Requires-Dist: yarl
Requires-Dist: zipp
